krash/__init__.py
krash/__main__.py
krash/cli.py
krash/env.py
krash/extractor.py
krash/resource.py
krash-0.1.0.dist-info/METADATA
krash-0.1.0.dist-info/WHEEL
krash-0.1.0.dist-info/entry_points.txt
krash-0.1.0.dist-info/licenses/LICENSE
krash-0.1.0.dist-info/RECORD
