Metadata-Version: 2.4
Name: krash
Version: 0.1.0
Summary: Tools for language learning based on comprehensible input
Author-email: Olav <olav.landsverk@gmail.com>
License-Expression: MIT
License-File: LICENSE
Classifier: Intended Audience :: End Users/Desktop
Requires-Python: >=3.13
Requires-Dist: click>=8.2.1
Requires-Dist: youtube-transcript-api>=1.1.1
